tap_bigquery/__init__.py
tap_bigquery/main.py
tap_bigquery/sync_bigquery.py
tap_bigquery/utils.py
tap_bigquery-0.3.10.dist-info/licenses/AUTHORS.md
tap_bigquery-0.3.10.dist-info/licenses/LICENSE
tap_bigquery-0.3.10.dist-info/METADATA
tap_bigquery-0.3.10.dist-info/WHEEL
tap_bigquery-0.3.10.dist-info/entry_points.txt
tap_bigquery-0.3.10.dist-info/top_level.txt
tap_bigquery-0.3.10.dist-info/RECORD
