Metadata-Version: 2.4
Name: tap-bigquery
Version: 0.3.10
Summary: Singer.io tap for extracting data from BigQuery
Author: Daigo Tanaka
License-Expression: Apache-2.0
Project-URL: Homepage, https://github.com/anelendata/tap-bigquery
Classifier: Development Status :: 4 - Beta
Classifier: Operating System :: MacOS :: MacOS X
Classifier: Operating System :: POSIX :: Linux
Classifier: Programming Language :: Python :: 3.9
Classifier: Programming Language :: Python :: 3.10
Classifier: Programming Language :: Python :: 3.11
Classifier: Programming Language :: Python :: 3.12
Requires-Python: >=3.9
License-File: LICENSE
License-File: AUTHORS.md
Requires-Dist: attrs==25.3.0
Requires-Dist: backoff>=1.8.0
Requires-Dist: getschema>=0.2.11
Requires-Dist: google-api-python-client>=2.133.0
Requires-Dist: google-cloud-bigquery==3.37.0
Requires-Dist: requests==2.32.5
Requires-Dist: simplejson==3.13.2
Requires-Dist: singer-python==6.1.1
Requires-Dist: numpy<2
Dynamic: license-file
